HowtodoinjavaQitaJiaocheng2ChuyiFix1/README.md
HowtodoinjavaQitaJiaocheng2ChuyiFix1/__init__.py
HowtodoinjavaQitaJiaocheng2ChuyiFix1/__main__.py
HowtodoinjavaQitaJiaocheng2ChuyiFix1/file.epub
HowtodoinjavaQitaJiaocheng2ChuyiFix1/index.html
HowtodoinjavaQitaJiaocheng2ChuyiFix1/css/__init__.py
HowtodoinjavaQitaJiaocheng2ChuyiFix1/css/annotations.css
HowtodoinjavaQitaJiaocheng2ChuyiFix1/css/main.css
HowtodoinjavaQitaJiaocheng2ChuyiFix1/css/normalize.css
HowtodoinjavaQitaJiaocheng2ChuyiFix1/css/popup.css
HowtodoinjavaQitaJiaocheng2ChuyiFix1/font/__init__.py
HowtodoinjavaQitaJiaocheng2ChuyiFix1/font/fontello.eot
HowtodoinjavaQitaJiaocheng2ChuyiFix1/font/fontello.svg
HowtodoinjavaQitaJiaocheng2ChuyiFix1/font/fontello.ttf
HowtodoinjavaQitaJiaocheng2ChuyiFix1/font/fontello.woff
HowtodoinjavaQitaJiaocheng2ChuyiFix1/img/__init__.py
HowtodoinjavaQitaJiaocheng2ChuyiFix1/img/annotator-glyph-sprite.png
HowtodoinjavaQitaJiaocheng2ChuyiFix1/img/annotator-icon-sprite.png
HowtodoinjavaQitaJiaocheng2ChuyiFix1/img/apple-touch-icon.png
HowtodoinjavaQitaJiaocheng2ChuyiFix1/img/cancelfullscreen.png
HowtodoinjavaQitaJiaocheng2ChuyiFix1/img/close.png
HowtodoinjavaQitaJiaocheng2ChuyiFix1/img/fullscreen.png
HowtodoinjavaQitaJiaocheng2ChuyiFix1/img/loader.gif
HowtodoinjavaQitaJiaocheng2ChuyiFix1/img/menu-icon.png
HowtodoinjavaQitaJiaocheng2ChuyiFix1/img/save.png
HowtodoinjavaQitaJiaocheng2ChuyiFix1/img/saved.png
HowtodoinjavaQitaJiaocheng2ChuyiFix1/img/settings-s.png
HowtodoinjavaQitaJiaocheng2ChuyiFix1/img/settings.png
HowtodoinjavaQitaJiaocheng2ChuyiFix1/img/star.png
HowtodoinjavaQitaJiaocheng2ChuyiFix1/js/__init__.py
HowtodoinjavaQitaJiaocheng2ChuyiFix1/js/epub.js
HowtodoinjavaQitaJiaocheng2ChuyiFix1/js/epub.min.js
HowtodoinjavaQitaJiaocheng2ChuyiFix1/js/epub.min.map
HowtodoinjavaQitaJiaocheng2ChuyiFix1/js/hooks.min.js
HowtodoinjavaQitaJiaocheng2ChuyiFix1/js/hooks.min.map
HowtodoinjavaQitaJiaocheng2ChuyiFix1/js/reader.js
HowtodoinjavaQitaJiaocheng2ChuyiFix1/js/reader.js.map
howtodoinjava_qita_jiaocheng_2_chuyi_fix1-2025.3.24.0.dist-info/METADATA
howtodoinjava_qita_jiaocheng_2_chuyi_fix1-2025.3.24.0.dist-info/WHEEL
howtodoinjava_qita_jiaocheng_2_chuyi_fix1-2025.3.24.0.dist-info/entry_points.txt
howtodoinjava_qita_jiaocheng_2_chuyi_fix1-2025.3.24.0.dist-info/top_level.txt
howtodoinjava_qita_jiaocheng_2_chuyi_fix1-2025.3.24.0.dist-info/RECORD
